loto/__init__.py
loto/loto.py
tests/__init__.py
tests/test_loto.py
loto-0.1.5.dist-info/LICENSE
loto-0.1.5.dist-info/METADATA
loto-0.1.5.dist-info/WHEEL
loto-0.1.5.dist-info/top_level.txt
loto-0.1.5.dist-info/RECORD
