Metadata-Version: 2.1
Name: loto
Version: 0.1.5
Summary: Decorator for tagging critical sections locking them out
Home-page: https://github.com/mardigontoler/loto
Author: Mardigon Toler
License: UNKNOWN
Platform: UNKNOWN
Classifier: Intended Audience :: Developers
Classifier: License :: OSI Approved :: MIT License
Classifier: Programming Language :: Python :: 3
Requires-Python: >=3
Requires-Dist: pytest
